lumberstack/__init__.py
lumberstack/common_noisy_loggers.py
lumberstack/constants.py
lumberstack/custom_handler.py
lumberstack/discord.py
lumberstack/exceptions.py
lumberstack/lumberstack.py
lumberstack-25.4.1600.dist-info/METADATA
lumberstack-25.4.1600.dist-info/WHEEL
lumberstack-25.4.1600.dist-info/licenses/LICENSE
lumberstack-25.4.1600.dist-info/RECORD
