Metadata-Version: 2.4
Name: lumberstack
Version: 25.4.1600
Summary: A simple abstraction of the logging package
Project-URL: Homepage, https://github.com/ghostdisco/lumberstack
Project-URL: Issues, https://github.com/ghostdisco/lumberstack/issues
Author-email: ghostdisco <pypi@ghostdisco.me>
License-File: LICENSE
Classifier: License :: OSI Approved :: BSD License
Classifier: Operating System :: OS Independent
Classifier: Programming Language :: Python :: 3
Requires-Python: >=3.8.1
Requires-Dist: logging>=0.4.9.6
Requires-Dist: requests
